AUTHORS.md
LICENSE
README.md
pyproject.toml
setup.cfg
setup.py
rele/__init__.py
rele/__main__.py
rele/apps.py
rele/client.py
rele/config.py
rele/discover.py
rele/middleware.py
rele/publishing.py
rele/retry_policy.py
rele/subscription.py
rele/worker.py
rele.egg-info/PKG-INFO
rele.egg-info/SOURCES.txt
rele.egg-info/dependency_links.txt
rele.egg-info/entry_points.txt
rele.egg-info/not-zip-safe
rele.egg-info/requires.txt
rele.egg-info/top_level.txt
rele/contrib/__init__.py
rele/contrib/django_db_middleware.py
rele/contrib/flask_middleware.py
rele/contrib/logging_middleware.py
rele/contrib/unrecoverable_middleware.py
rele/contrib/verbose_logging_middleware.py
rele/management/__init__.py
rele/management/discover.py
rele/management/commands/__init__.py
rele/management/commands/runrele.py
rele/management/commands/showsubscriptions.py
tests/commands/__init__.py
tests/commands/test_runrele.py
tests/commands/test_showsubscriptions.py
tests/management/__init__.py
tests/management/test_discover.py
tests/more_subs/__init__.py
tests/more_subs/subs.py
tests/sample_app/__init__.py
tests/sample_app/subs.py
tests/sample_app/another_folder/__init__.py
tests/sample_app/another_folder/subs.py
tests/sample_app/infrastructure/__init__.py
tests/sample_app/infrastructure/subs/__init__.py
tests/sample_app/infrastructure/subs/a_sub_file.py
tests/sample_app_2/__init__.py
tests/sample_app_2/a_folder/__init__.py
tests/sample_app_2/a_folder/subs.py
tests/sample_app_2/infrastructure/__init__.py
tests/sample_app_2/infrastructure/subs/__init__.py
tests/sample_app_2/infrastructure/subs/a_sub_file.py
tests/sample_app_2/subs/__init__.py
tests/sample_app_2/subs/another_sub_file.py